LICENSE
README.md
setup.cfg
setup.py
phyto_photo_utils/__init__.py
phyto_photo_utils/_equations.py
phyto_photo_utils/_etr.py
phyto_photo_utils/_fitting.py
phyto_photo_utils/_load.py
phyto_photo_utils/_plot.py
phyto_photo_utils/_relaxation.py
phyto_photo_utils/_saturation.py
phyto_photo_utils/_spectral_correction.py
phyto_photo_utils/_tools.py
phyto_photo_utils.egg-info/PKG-INFO
phyto_photo_utils.egg-info/SOURCES.txt
phyto_photo_utils.egg-info/dependency_links.txt
phyto_photo_utils.egg-info/requires.txt
phyto_photo_utils.egg-info/top_level.txt