Metadata-Version: 2.1
Name: phyto-photo-utils
Version: 1.5.1
Summary: Tools and utilities for active chlorophyll fluorescence data processing.
Home-page: https://gitlab.com/tjryankeogh/phytophotoutils
Download-URL: https://gitlab.com/tjryankeogh/phytophotoutils/-/archive/v1.4.6/phytophotoutils-v1.4.6.tar.gz
Author: Thomas Ryan-Keogh, Charlotte Robinson
Author-email: tjryankeogh@gmail.com
License: MIT License
License-File: LICENSE
